LICENSE.md
MANIFEST.in
README.md
requirements.txt
setup.cfg
setup.py
baitoolkit/.DS_Store
baitoolkit/__init__.py
baitoolkit.egg-info/PKG-INFO
baitoolkit.egg-info/SOURCES.txt
baitoolkit.egg-info/dependency_links.txt
baitoolkit.egg-info/not-zip-safe
baitoolkit.egg-info/requires.txt
baitoolkit.egg-info/top_level.txt
baitoolkit/auth/__init__.py
baitoolkit/auth/auth_constant.py
baitoolkit/auth/iam_client.py
baitoolkit/auth/rpc_proxy.py
baitoolkit/auth/user_token.py
baitoolkit/cli/.DS_Store
baitoolkit/cli/__init__.py
baitoolkit/cli/app_cli.py
baitoolkit/cli/localization_cli.py
baitoolkit/cli/rdb_migration_cli.py
baitoolkit/cli/test_cli.py
baitoolkit/cli/templates/.DS_Store
baitoolkit/cli/templates/rdb_migration_cli/alembic.ini.mako
baitoolkit/cli/templates/rdb_migration_cli/env.py.mako
baitoolkit/cli/templates/rdb_migration_cli/script.py.mako
baitoolkit/common/__init__.py
baitoolkit/common/constant.py
baitoolkit/common/context_manager.py
baitoolkit/common/file_util.py
baitoolkit/common/func_util.py
baitoolkit/common/jinja_extension.py
baitoolkit/common/localization.py
baitoolkit/common/logger_factory.py
baitoolkit/common/security.py
baitoolkit/common/starter.py
baitoolkit/common/type_util.py
baitoolkit/database/__init__.py
baitoolkit/database/dbclient_manager.py
baitoolkit/database/rdb_alchemy.py
baitoolkit/database/rdb_table.py
baitoolkit/database/dbclients/__init__.py
baitoolkit/database/dbclients/dbclient_base.py
baitoolkit/database/dbclients/mysql_client.py
baitoolkit/database/dbclients/nacos_client.py
baitoolkit/database/dbclients/pgsql_client.py
baitoolkit/database/dbclients/zookeeper_client.py
baitoolkit/exception/__init__.py
baitoolkit/exception/assert_util.py
baitoolkit/exception/errors.py
baitoolkit/parallel/__init__.py
baitoolkit/parallel/mutex.py
baitoolkit/parallel/nowait_call.py
baitoolkit/parallel/queue_call.py
baitoolkit/parallel/wait_call.py
baitoolkit/param/__init__.py
baitoolkit/param/illegalwords.txt
baitoolkit/param/param_parser.py
baitoolkit/param/param_validator.py
baitoolkit/web/__init__.py
baitoolkit/web/blueprint.py
baitoolkit/web/flaskapp_manager.py
baitoolkit/web/html_parser.py
baitoolkit/web/req_util.py
baitoolkit/web/web_constant.py
